static_npm/__init__.py
static_npm/cli.py
static_npm/ensure_npm_exists.py
static_npm/node.py
static_npm/npm.py
static_npm/npm_tool.py
static_npm/npx.py
static_npm/paths.py
static_npm/prog_exec.py
static_npm/running_process.py
static_npm/assets/example.txt
static_npm-1.0.13.dist-info/LICENSE
static_npm-1.0.13.dist-info/METADATA
static_npm-1.0.13.dist-info/WHEEL
static_npm-1.0.13.dist-info/entry_points.txt
static_npm-1.0.13.dist-info/top_level.txt
static_npm-1.0.13.dist-info/RECORD
