Metadata-Version: 2.1
Name: static_npm
Version: 1.0.13
Summary: static binaries of npm and node
Home-page: https://github.com/zackees/static-npm
Maintainer: Zachary Vorhies
License: BSD 3-Clause License
Keywords: template-python-cmd
Classifier: Programming Language :: Python :: 3
Requires-Python: >=3.10
License-File: LICENSE
Requires-Dist: download
Requires-Dist: appdirs
Requires-Dist: filelock
Requires-Dist: httpx
